{
  "$schema": "https://developer.microsoft.com/json-schemas/fabric/item/ontology/contextualization/1.0.0/schema.json",
  "id": "af42e11f-e22e-5780-b595-0a009a733800",
  "dataBindingTable": {
    "workspaceId": "7235ab18-0ba4-441e-b633-bc57f9e82ffa",
    "itemId": "59af920f-869b-4b7b-9a0e-2d30ac271edc",
    "sourceTableName": "bookings",
    "sourceSchema": "dbo",
    "sourceType": "LakehouseTable"
  },
  "sourceKeyRefBindings": [
    {
      "sourceColumnName": "booking_id",
      "targetPropertyId": "4544038892445289158"
    }
  ],
  "targetKeyRefBindings": [
    {
      "sourceColumnName": "property_id",
      "targetPropertyId": "6543400353261354367"
    }
  ]
}